{
  "characters": [
    {
      "id": 0,
      "name": "胡斐",
      "source": "雪山飞狐"
    },
    {
      "id": 1,
      "name": "段誉",
      "source": "天龙八部"
    },
    {
      "id": 2,
      "name": "乔峰",
      "source": "天龙八部"
    },
    {
      "id": 3,
      "name": "虚竹",
      "source": "天龙八部"
    },
    {
      "id": 4,
      "name": "令狐冲",
      "source": "笑傲江湖"
    },
    {
      "id": 5,
      "name": "郭靖",
      "source": "射雕英雄传"
    },
    {
      "id": 6,
      "name": "杨过",
      "source": "神雕侠侣"
    },
    {
      "id": 7,
      "name": "张无忌",
      "source": "倚天屠龙记"
    },
    {
      "id": 8,
      "name": "黄蓉",
      "source": "射雕英雄传"
    },
    {
      "id": 9,
      "name": "小龙女",
      "source": "神雕侠侣"
    },
    {
      "id": 10,
      "name": "洪七公",
      "source": "射雕英雄传"
    },
    {
      "id": 11,
      "name": "黄药师",
      "source": "射雕英雄传"
    },
    {
      "id": 12,
      "name": "欧阳锋",
      "source": "射雕英雄传"
    },
    {
      "id": 13,
      "name": "王重阳",
      "source": "射雕英雄传"
    },
    {
      "id": 14,
      "name": "东方不败",
      "source": "笑傲江湖"
    },
    {
      "id": 15,
      "name": "张三丰",
      "source": "倚天屠龙记"
    },
    {
      "id": 16,
      "name": "周伯通",
      "source": "射雕英雄传"
    },
    {
      "id": 17,
      "name": "独孤求败",
      "source": "神雕侠侣（传说）"
    },
    {
      "id": 18,
      "name": "王语嫣",
      "source": "天龙八部"
    },
    {
      "id": 19,
      "name": "慕容复",
      "source": "天龙八部"
    },
    {
      "id": 20,
      "name": "鸠摩智",
      "source": "天龙八部"
    },
    {
      "id": 21,
      "name": "段正淳",
      "source": "天龙八部"
    },
    {
      "id": 22,
      "name": "萧远山",
      "source": "天龙八部"
    },
    {
      "id": 23,
      "name": "扫地僧",
      "source": "天龙八部"
    },
    {
      "id": 24,
      "name": "阿朱",
      "source": "天龙八部"
    },
    {
      "id": 25,
      "name": "阿紫",
      "source": "天龙八部"
    },
    {
      "id": 26,
      "name": "郭襄",
      "source": "神雕侠侣"
    },
    {
      "id": 27,
      "name": "金轮法王",
      "source": "神雕侠侣"
    },
    {
      "id": 28,
      "name": "李莫愁",
      "source": "神雕侠侣"
    },
    {
      "id": 29,
      "name": "公孙止",
      "source": "神雕侠侣"
    },
    {
      "id": 30,
      "name": "霍都",
      "source": "神雕侠侣"
    },
    {
      "id": 31,
      "name": "耶律齐",
      "source": "神雕侠侣"
    },
    {
      "id": 32,
      "name": "程英",
      "source": "神雕侠侣"
    },
    {
      "id": 33,
      "name": "陆无双",
      "source": "神雕侠侣"
    },
    {
      "id": 34,
      "name": "游坦之",
      "source": "天龙八部"
    },
    {
      "id": 35,
      "name": "慕容博",
      "source": "天龙八部"
    },
    {
      "id": 36,
      "name": "达尔巴",
      "source": "神雕侠侣"
    },
    {
      "id": 37,
      "name": "赵敏",
      "source": "倚天屠龙记"
    },
    {
      "id": 38,
      "name": "周芷若",
      "source": "倚天屠龙记"
    },
    {
      "id": 39,
      "name": "谢逊",
      "source": "倚天屠龙记"
    },
    {
      "id": 40,
      "name": "成昆",
      "source": "倚天屠龙记"
    },
    {
      "id": 41,
      "name": "灭绝师太",
      "source": "倚天屠龙记"
    },
    {
      "id": 42,
      "name": "张翠山",
      "source": "倚天屠龙记"
    },
    {
      "id": 43,
      "name": "殷素素",
      "source": "倚天屠龙记"
    },
    {
      "id": 44,
      "name": "宋远桥",
      "source": "倚天屠龙记"
    },
    {
      "id": 45,
      "name": "杨逍",
      "source": "倚天屠龙记"
    },
    {
      "id": 46,
      "name": "范遥",
      "source": "倚天屠龙记"
    },
    {
      "id": 47,
      "name": "小昭",
      "source": "倚天屠龙记"
    },
    {
      "id": 48,
      "name": "殷天正",
      "source": "倚天屠龙记"
    },
    {
      "id": 49,
      "name": "任我行",
      "source": "笑傲江湖"
    },
    {
      "id": 50,
      "name": "岳不群",
      "source": "笑傲江湖"
    },
    {
      "id": 51,
      "name": "任盈盈",
      "source": "笑傲江湖"
    },
    {
      "id": 52,
      "name": "向问天",
      "source": "笑傲江湖"
    },
    {
      "id": 53,
      "name": "田伯光",
      "source": "笑傲江湖"
    },
    {
      "id": 54,
      "name": "仪琳",
      "source": "笑傲江湖"
    },
    {
      "id": 55,
      "name": "韦小宝",
      "source": "鹿鼎记"
    },
    {
      "id": 56,
      "name": "康熙",
      "source": "鹿鼎记"
    },
    {
      "id": 57,
      "name": "陈近南",
      "source": "鹿鼎记"
    },
    {
      "id": 58,
      "name": "洪安通",
      "source": "鹿鼎记"
    },
    {
      "id": 59,
      "name": "苏荃",
      "source": "鹿鼎记"
    },
    {
      "id": 60,
      "name": "双儿",
      "source": "鹿鼎记"
    },
    {
      "id": 61,
      "name": "陈家洛",
      "source": "书剑恩仇录"
    },
    {
      "id": 62,
      "name": "霍青桐",
      "source": "书剑恩仇录"
    },
    {
      "id": 63,
      "name": "袁承志",
      "source": "碧血剑"
    },
    {
      "id": 64,
      "name": "温青青",
      "source": "碧血剑"
    },
    {
      "id": 65,
      "name": "石破天",
      "source": "侠客行"
    },
    {
      "id": 66,
      "name": "狄云",
      "source": "连城诀"
    },
    {
      "id": 67,
      "name": "胡一刀",
      "source": "雪山飞狐"
    },
    {
      "id": 68,
      "name": "苗人凤",
      "source": "雪山飞狐"
    },
    {
      "id": 69,
      "name": "程灵素",
      "source": "雪山飞狐"
    },
    {
      "id": 70,
      "name": "段正明",
      "source": "天龙八部"
    },
    {
      "id": 71,
      "name": "刀白凤",
      "source": "天龙八部"
    },
    {
      "id": 72,
      "name": "丁春秋",
      "source": "天龙八部"
    },
    {
      "id": 73,
      "name": "无崖子",
      "source": "天龙八部"
    },
    {
      "id": 74,
      "name": "天山童姥",
      "source": "天龙八部"
    },
    {
      "id": 75,
      "name": "李秋水",
      "source": "天龙八部"
    },
    {
      "id": 76,
      "name": "苏星河",
      "source": "天龙八部"
    },
    {
      "id": 77,
      "name": "康敏",
      "source": "天龙八部"
    },
    {
      "id": 78,
      "name": "全冠清",
      "source": "天龙八部"
    },
    {
      "id": 79,
      "name": "甘宝宝",
      "source": "天龙八部"
    },
    {
      "id": 80,
      "name": "阮星竹",
      "source": "天龙八部"
    },
    {
      "id": 81,
      "name": "秦红棉",
      "source": "天龙八部"
    },
    {
      "id": 82,
      "name": "建宁公主",
      "source": "鹿鼎记"
    },
    {
      "id": 83,
      "name": "海大富",
      "source": "鹿鼎记"
    },
    {
      "id": 84,
      "name": "鳌拜",
      "source": "鹿鼎记"
    },
    {
      "id": 85,
      "name": "多隆",
      "source": "鹿鼎记"
    },
    {
      "id": 86,
      "name": "吴三桂",
      "source": "鹿鼎记"
    },
    {
      "id": 87,
      "name": "吴应熊",
      "source": "鹿鼎记"
    },
    {
      "id": 88,
      "name": "风际中",
      "source": "鹿鼎记"
    },
    {
      "id": 89,
      "name": "沐剑屏",
      "source": "鹿鼎记"
    },
    {
      "id": 90,
      "name": "方怡",
      "source": "鹿鼎记"
    },
    {
      "id": 91,
      "name": "曾柔",
      "source": "鹿鼎记"
    },
    {
      "id": 92,
      "name": "阿珂",
      "source": "鹿鼎记"
    },
    {
      "id": 93,
      "name": "夏雪宜",
      "source": "碧血剑"
    },
    {
      "id": 94,
      "name": "温仪",
      "source": "碧血剑"
    },
    {
      "id": 95,
      "name": "何铁手",
      "source": "碧血剑"
    },
    {
      "id": 96,
      "name": "温方达",
      "source": "碧血剑"
    },
    {
      "id": 97,
      "name": "温方义",
      "source": "碧血剑"
    },
    {
      "id": 98,
      "name": "焦宛儿",
      "source": "碧血剑"
    },
    {
      "id": 99,
      "name": "安小慧",
      "source": "碧血剑"
    },
    {
      "id": 100,
      "name": "白阿绣",
      "source": "侠客行"
    },
    {
      "id": 101,
      "name": "白自在",
      "source": "侠客行"
    },
    {
      "id": 102,
      "name": "贝海石",
      "source": "侠客行"
    },
    {
      "id": 103,
      "name": "谢烟客",
      "source": "侠客行"
    },
    {
      "id": 104,
      "name": "丁珰",
      "source": "侠客行"
    },
    {
      "id": 105,
      "name": "水笙",
      "source": "连城诀"
    },
    {
      "id": 106,
      "name": "丁典",
      "source": "连城诀"
    },
    {
      "id": 107,
      "name": "戚芳",
      "source": "连城诀"
    },
    {
      "id": 108,
      "name": "万圭",
      "source": "连城诀"
    },
    {
      "id": 109,
      "name": "凌退思",
      "source": "连城诀"
    },
    {
      "id": 110,
      "name": "血刀老祖",
      "source": "连城诀"
    },
    {
      "id": 200,
      "name": "山贼",
      "source": "通用敌人"
    },
    {
      "id": 201,
      "name": "强盗",
      "source": "通用敌人"
    },
    {
      "id": 202,
      "name": "武林高手",
      "source": "通用敌人"
    },
    {
      "id": 300,
      "name": "村长",
      "source": "通用NPC"
    },
    {
      "id": 301,
      "name": "商人",
      "source": "通用NPC"
    }
  ]
}